mirai/__init__.py
mirai/exceptions.py
mirai/face.py
mirai/friend.py
mirai/group.py
mirai/logger.py
mirai/misc.py
mirai/network.py
mirai/protocol.py
mirai/session.py
kuriyama-0.1.1.dist-info/LICENSE
kuriyama-0.1.1.dist-info/METADATA
kuriyama-0.1.1.dist-info/WHEEL
kuriyama-0.1.1.dist-info/top_level.txt
kuriyama-0.1.1.dist-info/RECORD
