Metadata-Version: 2.1
Name: kuriyama
Version: 0.1.1
Summary: A framework for OICQ(QQ, made by Tencent) headless client "Mirai".
Home-page: https://github.com/Chenwe-i-lin/python-mirai
Author: Chenwe-i-lin
Author-email: Chenwe_i_lin@outlook.com
License: UNKNOWN
Keywords: oicq qq qqbot
Platform: UNKNOWN
Classifier: Development Status :: 4 - Beta
Classifier: Intended Audience :: Developers
Classifier: Topic :: Software Development :: User Interfaces
Classifier: License :: OSI Approved :: MIT License
Classifier: Programming Language :: Python :: 3.7
Classifier: Operating System :: OS Independent
Requires-Python: >=3.7
